btconfig/__init__.py
btconfig/configloader.py
btconfig/configutils.py
btconfig/logger.py
btconfig/superconf.py
btconfig-5.1.0.dist-info/METADATA
btconfig-5.1.0.dist-info/WHEEL
btconfig-5.1.0.dist-info/top_level.txt
btconfig-5.1.0.dist-info/RECORD
