Metadata-Version: 2.4
Name: btconfig
Version: 5.1.0
Summary: Module for reading configuration files
Home-page: https://github.com/berttejeda/bert.config
Author: Engelbert Tejeda
Author-email: berttejeda@gmail.com
Keywords: yaml,configuration,config,file,python,settings
Classifier: Development Status :: 3 - Alpha
Classifier: Intended Audience :: Developers
Classifier: Intended Audience :: Information Technology
Classifier: License :: OSI Approved :: MIT License
Classifier: Natural Language :: English
Classifier: Programming Language :: Python :: 3.7
Classifier: Programming Language :: Python :: 3.8
Classifier: Programming Language :: Python :: 3.9
Classifier: Programming Language :: Python :: 3.10
Classifier: Programming Language :: Python :: 3.11
Classifier: Programming Language :: Python :: 3.12
Requires-Python: >=3.7
Requires-Dist: jinja2
Requires-Dist: PyYAML
Requires-Dist: requests
Requires-Dist: btweb
Provides-Extra: tests
Requires-Dist: pytest; extra == "tests"
Requires-Dist: pytest-cov; extra == "tests"
Requires-Dist: coveralls; extra == "tests"
Requires-Dist: flake8; extra == "tests"
Requires-Dist: mypy; extra == "tests"
